data_source/__init__.py
data_source/base/__init__.py
data_source/base/base.py
data_source/base/utility/__init__.py
data_source/base/utility/download.py
data_source/compound/__init__.py
data_source/compound/compound.py
data_source/compound/chembl/__init__.py
data_source/compound/chembl/chembl.py
data_source/compound/chembl/utility/__init__.py
data_source/compound/chembl/utility/download.py
data_source/compound/chembl/utility/extraction.py
data_source/compound/chembl/utility/formatting.py
data_source/compound/coconut/__init__.py
data_source/compound/coconut/coconut.py
data_source/compound/coconut/utility/__init__.py
data_source/compound/coconut/utility/download.py
data_source/compound/coconut/utility/extraction.py
data_source/compound/coconut/utility/formatting.py
data_source/compound/miscellaneous/__init__.py
data_source/compound/miscellaneous/miscellaneous.py
data_source/compound/miscellaneous/utility/__init__.py
data_source/compound/miscellaneous/utility/download.py
data_source/compound/miscellaneous/utility/extraction.py
data_source/compound/miscellaneous/utility/formatting.py
data_source/compound/zinc/__init__.py
data_source/compound/zinc/zinc.py
data_source/compound/zinc/utility/__init__.py
data_source/compound/zinc/utility/download.py
data_source/compound/zinc/utility/extraction.py
data_source/compound/zinc/utility/formatting.py
data_source/compound_pattern/__init__.py
data_source/compound_pattern/compound_pattern.py
data_source/compound_pattern/rdkit/__init__.py
data_source/compound_pattern/rdkit/rdkit.py
data_source/compound_pattern/rdkit/utility/__init__.py
data_source/compound_pattern/rdkit/utility/download.py
data_source/compound_pattern/rdkit/utility/extraction.py
data_source/compound_pattern/rdkit/utility/formatting.py
data_source/reaction/__init__.py
data_source/reaction/reaction.py
data_source/reaction/crd/__init__.py
data_source/reaction/crd/crd.py
data_source/reaction/crd/utility/__init__.py
data_source/reaction/crd/utility/download.py
ncsw_data_source-2025.9.2.dist-info/licenses/LICENSE
ncsw_data_source-2025.9.2.dist-info/METADATA
ncsw_data_source-2025.9.2.dist-info/WHEEL
ncsw_data_source-2025.9.2.dist-info/top_level.txt
ncsw_data_source-2025.9.2.dist-info/RECORD
