Metadata-Version: 2.4
Name: ncsw-data-source
Version: 2025.9.2
Summary: The computer-assisted chemical synthesis data source research project.
Author: Haris Hasic
Keywords: chemical-compound-patterns,,chemical-compounds,,chemical-reaction-patterns,,chemical-reactions,,data,,data-source,,database,,dataset
License-File: LICENSE
Requires-Dist: ord-schema
Requires-Dist: py7zr
Requires-Dist: pyarrow
Requires-Dist: pqdm
Requires-Dist: rdkit
Requires-Dist: requests
Requires-Dist: tqdm
Dynamic: license-file
